iupdate/__init__.py
iupdate/iupdate.py
iupdate/lib/__init__.py
iupdate/lib/ansi_code.py
iupdate-0.0.1.dist-info/LICENSE
iupdate-0.0.1.dist-info/METADATA
iupdate-0.0.1.dist-info/WHEEL
iupdate-0.0.1.dist-info/entry_points.txt
iupdate-0.0.1.dist-info/top_level.txt
iupdate-0.0.1.dist-info/RECORD
